secoda_airflow/__init__.py
secoda_airflow/callbacks.py
secoda_airflow/get_provider_info.py
secoda_airflow/hooks.py
secoda_airflow-0.0.26.dist-info/LICENSE
secoda_airflow-0.0.26.dist-info/METADATA
secoda_airflow-0.0.26.dist-info/WHEEL
secoda_airflow-0.0.26.dist-info/entry_points.txt
secoda_airflow-0.0.26.dist-info/top_level.txt
secoda_airflow-0.0.26.dist-info/RECORD
